openai_stt/__init__.py
openai_stt/stt.py
openai_stt-2.2.1.dist-info/METADATA
openai_stt-2.2.1.dist-info/WHEEL
openai_stt-2.2.1.dist-info/top_level.txt
openai_stt-2.2.1.dist-info/RECORD
