Metadata-Version: 2.4
Name: openai_stt
Version: 2.2.1
Summary: Speech-to-Text tool using Whisper, PyAudio, and VAD.
Author-email: Advik Mathur <pranit.advik@gmail.com>
Requires-Python: >=3.13
Requires-Dist: pyaudio
Requires-Dist: webrtcvad
Requires-Dist: keyboard
Requires-Dist: syntaxmod
Requires-Dist: openai-whisper
Requires-Dist: faster-whisper
Requires-Dist: openai
Requires-Dist: setuptools
